dianna/__init__.py
dianna/_logging_utils.py
dianna/cli.py
dianna/dashboard/Home.py
dianna/dashboard/_image_utils.py
dianna/dashboard/_model_utils.py
dianna/dashboard/_models_image.py
dianna/dashboard/_models_tabular.py
dianna/dashboard/_models_text.py
dianna/dashboard/_models_ts.py
dianna/dashboard/_movie_model.py
dianna/dashboard/_shared.py
dianna/dashboard/_ts_utils.py
dianna/dashboard/readme.md
dianna/dashboard/.streamlit/config.toml
dianna/dashboard/pages/Images.py
dianna/dashboard/pages/Tabular.py
dianna/dashboard/pages/Text.py
dianna/dashboard/pages/Time_series.py
dianna/data/Diana_goddess.png
dianna/data/FRB211024.npy
dianna/data/bee.jpg
dianna/data/binary-mnist.npz
dianna/data/colormap.png
dianna/data/digit0.jpg
dianna/data/digit1.png
dianna/data/leafsnap_example_acer_rubrum.jpg
dianna/data/logo.png
dianna/data/movie_reviews_word_vectors.txt
dianna/data/weather_data.npy
dianna/labels/apertif_frb_classes.txt
dianna/labels/labels_mnist.txt
dianna/labels/labels_resnet50.txt
dianna/labels/labels_text.txt
dianna/labels/leafsnap_classes.csv
dianna/labels/weather_data_labels.txt
dianna/methods/kernelshap_image.py
dianna/methods/kernelshap_tabular.py
dianna/methods/lime_image.py
dianna/methods/lime_tabular.py
dianna/methods/lime_text.py
dianna/methods/lime_timeseries.py
dianna/methods/rise_image.py
dianna/methods/rise_tabular.py
dianna/methods/rise_text.py
dianna/methods/rise_timeseries.py
dianna/models/mnist_model_tf.onnx
dianna/models/season_prediction_model_temp_max_binary.onnx
dianna/utils/__init__.py
dianna/utils/downloader.py
dianna/utils/maskers.py
dianna/utils/misc.py
dianna/utils/onnx_runner.py
dianna/utils/predict.py
dianna/utils/rise_utils.py
dianna/utils/tokenizers.py
dianna/visualization/__init__.py
dianna/visualization/image.py
dianna/visualization/tabular.py
dianna/visualization/text.py
dianna/visualization/timeseries.py
dianna-1.7.0.dist-info/LICENSE
dianna-1.7.0.dist-info/METADATA
dianna-1.7.0.dist-info/WHEEL
dianna-1.7.0.dist-info/entry_points.txt
dianna-1.7.0.dist-info/top_level.txt
dianna-1.7.0.dist-info/RECORD
