Metadata-Version: 2.1
Name: dianna
Version: 1.7.0
Summary: Deep Insight And Neural Network Analysis
Home-page: https://github.com/dianna-ai/dianna
Author: DIANNA Team
Author-email: dianna-ai@esciencecenter.nl
License: Apache License 2.0
Project-URL: Bug Tracker, https://github.com/dianna-ai/dianna/issues
Keywords: XAI,machine learning
Classifier: Development Status :: 2 - Pre-Alpha
Classifier: Intended Audience :: Developers
Classifier: License :: OSI Approved :: Apache Software License
Classifier: Natural Language :: English
Classifier: Programming Language :: Python :: 3
Classifier: Programming Language :: Python :: 3.8
Classifier: Programming Language :: Python :: 3.9
Classifier: Programming Language :: Python :: 3.10
Classifier: Programming Language :: Python :: 3.11
Requires-Python: <3.12,>=3.8
License-File: LICENSE
Requires-Dist: fastdtw
Requires-Dist: ipython
Requires-Dist: lime
Requires-Dist: matplotlib
Requires-Dist: numpy>=1.20
Requires-Dist: onnx==1.14.1
Requires-Dist: onnx-tf
Requires-Dist: onnxruntime
Requires-Dist: pooch
Requires-Dist: shap<0.45
Requires-Dist: scikit-image>=0.19.3
Requires-Dist: scikit-learn
Requires-Dist: tqdm
Requires-Dist: xarray
Requires-Dist: pandas
Requires-Dist: torch<=2.3.1
Requires-Dist: tensorflow<2.16,>=2.12
Requires-Dist: tensorflow-probability<0.24
Requires-Dist: importlib-resources; python_version < "3.10"
Provides-Extra: dashboard
Requires-Dist: keras; extra == "dashboard"
Requires-Dist: Pillow; extra == "dashboard"
Requires-Dist: plotly; extra == "dashboard"
Requires-Dist: scipy; extra == "dashboard"
Requires-Dist: seaborn; extra == "dashboard"
Requires-Dist: spacy<3.8.0; extra == "dashboard"
Requires-Dist: streamlit-aggrid; extra == "dashboard"
Requires-Dist: streamlit; extra == "dashboard"
Requires-Dist: streamlit-option-menu; extra == "dashboard"
Requires-Dist: transformers; extra == "dashboard"
Requires-Dist: xgboost; extra == "dashboard"
Requires-Dist: importlib-resources; python_version < "3.10" and extra == "dashboard"
Provides-Extra: dev
Requires-Dist: bump2version; extra == "dev"
Requires-Dist: pre-commit; extra == "dev"
Requires-Dist: scipy; extra == "dev"
Requires-Dist: spacy<3.8.0; extra == "dev"
Requires-Dist: coverage[toml]; extra == "dev"
Requires-Dist: pytest; extra == "dev"
Requires-Dist: pytest-cov; extra == "dev"
Requires-Dist: pytest-playwright; extra == "dev"
Provides-Extra: docs
Requires-Dist: myst-parser; extra == "docs"
Requires-Dist: nbmake; extra == "docs"
Requires-Dist: nbsphinx; extra == "docs"
Requires-Dist: nbsphinx-link; extra == "docs"
Requires-Dist: pandoc; extra == "docs"
Requires-Dist: sphinx; extra == "docs"
Requires-Dist: sphinx-autoapi; extra == "docs"
Requires-Dist: sphinx-rtd-theme; extra == "docs"
Provides-Extra: notebooks
Requires-Dist: keras; extra == "notebooks"
Requires-Dist: nbmake; extra == "notebooks"
Requires-Dist: notebook; extra == "notebooks"
Requires-Dist: Pillow; extra == "notebooks"
Requires-Dist: pytorch-lightning; extra == "notebooks"
Requires-Dist: scipy; extra == "notebooks"
Requires-Dist: skl2onnx; extra == "notebooks"
Requires-Dist: spacy<3.8.0; extra == "notebooks"
Requires-Dist: seaborn; extra == "notebooks"
Requires-Dist: tf2onnx; extra == "notebooks"
Requires-Dist: torch; extra == "notebooks"
Requires-Dist: torchvision; extra == "notebooks"
Requires-Dist: ipywidgets; extra == "notebooks"
Requires-Dist: freetype-py; extra == "notebooks"
Requires-Dist: transformers<4.46.0; extra == "notebooks"
Requires-Dist: xgboost; extra == "notebooks"
Provides-Extra: publishing
Requires-Dist: build; extra == "publishing"
Requires-Dist: twine; extra == "publishing"
Requires-Dist: wheel; extra == "publishing"
Provides-Extra: text
Requires-Dist: spacy<3.8.0; extra == "text"
